LICENCE.md
README.md
pyproject.toml
setup.cfg
setup.py
src/pipeline/__init__.py
src/pipeline/exception.py
src/pipeline/pipeline.py
src/pipeline/queue.py
src/pipeline_turing_system.egg-info/PKG-INFO
src/pipeline_turing_system.egg-info/SOURCES.txt
src/pipeline_turing_system.egg-info/dependency_links.txt
src/pipeline_turing_system.egg-info/top_level.txt