Metadata-Version: 2.1
Name: pipeline-turing-system
Version: 1.0.0
Summary: Pipeline simplify multithread common use to few lines of code.
Home-page: UNKNOWN
Author: Vincent SALOME
Author-email: vincent.salome@turing-system.com
License: UNKNOWN
Platform: UNKNOWN
Classifier: Programming Language :: Python :: 3
Classifier: License :: OSI Approved :: MIT License
Classifier: Operating System :: OS Independent
Requires-Python: >=3.5
